setup.py
pydinog/Builder.py
pydinog/__init__.py
pydinog.egg-info/PKG-INFO
pydinog.egg-info/SOURCES.txt
pydinog.egg-info/dependency_links.txt
pydinog.egg-info/requires.txt
pydinog.egg-info/top_level.txt