Metadata-Version: 2.1
Name: pydinog
Version: 0.0.1
Summary: Sort description
Author: Ho Anh Tuan
Author-email: author@example.com
Classifier: Programming Language :: Python :: 2
Classifier: License :: OSI Approved :: MIT License
Classifier: Operating System :: OS Independent
